obliqueslice/__init__.py
obliqueslice/obliqueslice.py
obliqueslice-0.1.1.dist-info/licenses/LICENSE.txt
obliqueslice-0.1.1.dist-info/METADATA
obliqueslice-0.1.1.dist-info/WHEEL
obliqueslice-0.1.1.dist-info/top_level.txt
obliqueslice-0.1.1.dist-info/RECORD
