Metadata-Version: 2.4
Name: obliqueslice
Version: 0.1.1
Summary: A package for slicing 3D numpy arrays along an oblique plane. Equivalent to obliqueslice in MATLAB.
Home-page: https://github.com/junapsantos/obliqueslice
Author: Juna Santos
Author-email: junapsantos@tecnico.ulisboa.pt
Classifier: Programming Language :: Python :: 3
Classifier: License :: OSI Approved :: MIT License
Classifier: Operating System :: OS Independent
Requires-Python: >=3.6
License-File: LICENSE.txt
Requires-Dist: numpy
Requires-Dist: scipy
Dynamic: author
Dynamic: author-email
Dynamic: classifier
Dynamic: description
Dynamic: description-content-type
Dynamic: home-page
Dynamic: license-file
Dynamic: requires-dist
Dynamic: requires-python
Dynamic: summary
